pdsls/__init__.py
pdsls/cli.py
pdsls/py.typed
pdsls/_internal/__init__.py
pdsls/_internal/auth.py
pdsls/_internal/config.py
pdsls/_internal/display.py
pdsls/_internal/operations.py
pdsls/_internal/output.py
pdsls/_internal/parsing.py
pdsls/_internal/types.py
pdsls-0.0.1a2.dist-info/METADATA
pdsls-0.0.1a2.dist-info/WHEEL
pdsls-0.0.1a2.dist-info/entry_points.txt
pdsls-0.0.1a2.dist-info/RECORD
