Metadata-Version: 2.4
Name: pdsls
Version: 0.0.1a2
Summary: general-purpose cli for atproto record operations
Author-email: zzstoatzz <thrast36@gmail.com>
License-Expression: MIT
Keywords: atproto,bluesky,cli,pds,records
Classifier: Development Status :: 3 - Alpha
Classifier: Intended Audience :: Developers
Classifier: License :: OSI Approved :: MIT License
Classifier: Programming Language :: Python :: 3
Classifier: Programming Language :: Python :: 3.10
Classifier: Programming Language :: Python :: 3.11
Classifier: Programming Language :: Python :: 3.12
Classifier: Programming Language :: Python :: 3.13
Classifier: Programming Language :: Python :: 3.14
Classifier: Topic :: Software Development :: Libraries :: Python Modules
Classifier: Typing :: Typed
Requires-Python: >=3.10
Requires-Dist: atproto>=0.0.63
Requires-Dist: pydantic-settings>=2.7.0
Requires-Dist: rich>=13.0.0
